Workbook

Sheet Simulador
B2: SIMULADOR DE FUNDOS IMOBILIÁRIOS
B4: Parâmetros de entrada | E4: Indicadores
B5: Aporte mensal (R$) | C5: 500 | E5: Multiplicador do Capital | F5: =IF(C12=0,0,C13/C12) -> 1.6684789
B6: Período (meses) | C6: 120 | E6: Rend. Anualizado (%) | F6: =(1+C7)^12-1 -> 0.10033869
B7: Rendimento mensal (%) | C7: 0.008 | E7: Renda Passiva/Dia (R$) | F7: =C16/30 -> 26.695663
B8: Patrimônio inicial (R$) | C8: 0 | E8: Meta R$1k/mês — meses | F8: =IF(C7=0,"∞",IFERROR(LOG(1000/(C5*C7)+1,1+C7),"∞")) -> 693.44067
B9: Reinvestir dividendos? | C9: SIM | E9: Aporte p/ R$5k/mês (R$) | F9: =IF(C7=0,0,5000/((1+C7)^C6-1)*C7) -> 24.972846
B11: Resultados | E11: Observações
B12: Total investido (R$) | C12: =C5*C6+C8 -> 60000 | E12: Fundos imobiliários podem pagar dividendos mensais.
B13: Patrimônio Acumulado (R$) | C13: =IF(C9="SIM",C8*(1+C7)^C6+C5*((1+C7)^C6-1)/C7,C8+C5*C6+C8*C7*C6+C5*C7*C6*(C6+1)/2) -> 100108.73 | E13: Os valores são apenas uma simulação.
B14: Rendimento Total (R$) | C14: =C13-C12 -> 40108.735 | E14: O rendimento pode variar ao longo do tempo.
B15: Rentabilidade Total (%) | C15: =IF(C12=0,0,(C13-C12)/C12) -> 0.66847891 | E15: Diversifique entre FIIs de papel, tijolo e híbridos.
B16: Dividendos Mensais (R$) | C16: =C13*C7 -> 800.86988 | E16: Analise o P/VP e o DY antes de escolher o fundo.
B17: Dividendos Anuais (R$) | C17: =C16*12 -> 9610.4385 | E17: Consulte sempre um assessor antes de investir.

Sheet Evolução Mensal
B2: EVOLUÇÃO MENSAL
B4: Mês | C4: Total Investido (R$) | D4: Patrimônio (R$) | E4: Rendimento Mês (R$) | F4: Dividendos Acum. (R$)
B5: 1 | C5: =Simulador!$C$8+Simulador!$C$5*B5 -> 500 | D5: =IF(Simulador!$C$9="SIM",(Simulador!$C$8+Simulador!$C$5)*(1+Simulador!$C$7),Simulador!$C$8+Simulador!$C$5+Simulador!$C$8*Simulador!$C$7) -> 504 | E5: =D5*Simulador!$C$7 -> 4.032 | F5: =E5 -> 4.032
B6: 2 | C6: =Simulador!$C$8+Simulador!$C$5*B6 -> 1000 | D6: =IF(Simulador!$C$9="SIM",(D5+Simulador!$C$5)*(1+Simulador!$C$7),D5+Simulador!$C$5+D5*Simulador!$C$7) -> 1012.032 | E6: =D6*Simulador!$C$7 -> 8.096256 | F6: =F5+E6 -> 12.128256
B7: 3 | C7: =Simulador!$C$8+Simulador!$C$5*B7 -> 1500 | D7: =IF(Simulador!$C$9="SIM",(D6+Simulador!$C$5)*(1+Simulador!$C$7),D6+Simulador!$C$5+D6*Simulador!$C$7) -> 1524.1283 | E7: =D7*Simulador!$C$7 -> 12.193026 | F7: =F6+E7 -> 24.321282
B8: 4 | C8: =Simulador!$C$8+Simulador!$C$5*B8 -> 2000 | D8: =IF(Simulador!$C$9="SIM",(D7+Simulador!$C$5)*(1+Simulador!$C$7),D7+Simulador!$C$5+D7*Simulador!$C$7) -> 2040.3213 | E8: =D8*Simulador!$C$7 -> 16.32257 | F8: =F7+E8 -> 40.643852
B9: 5 | C9: =Simulador!$C$8+Simulador!$C$5*B9 -> 2500 | D9: =IF(Simulador!$C$9="SIM",(D8+Simulador!$C$5)*(1+Simulador!$C$7),D8+Simulador!$C$5+D8*Simulador!$C$7) -> 2560.6439 | E9: =D9*Simulador!$C$7 -> 20.485151 | F9: =F8+E9 -> 61.129003
B10: 6 | C10: =Simulador!$C$8+Simulador!$C$5*B10 -> 3000 | D10: =IF(Simulador!$C$9="SIM",(D9+Simulador!$C$5)*(1+Simulador!$C$7),D9+Simulador!$C$5+D9*Simulador!$C$7) -> 3085.129 | E10: =D10*Simulador!$C$7 -> 24.681032 | F10: =F9+E10 -> 85.810035 | I10: .
B11: 7 | C11: =Simulador!$C$8+Simulador!$C$5*B11 -> 3500 | D11: =IF(Simulador!$C$9="SIM",(D10+Simulador!$C$5)*(1+Simulador!$C$7),D10+Simulador!$C$5+D10*Simulador!$C$7) -> 3613.81 | E11: =D11*Simulador!$C$7 -> 28.91048 | F11: =F10+E11 -> 114.72052
B12: 8 | C12: =Simulador!$C$8+Simulador!$C$5*B12 -> 4000 | D12: =IF(Simulador!$C$9="SIM",(D11+Simulador!$C$5)*(1+Simulador!$C$7),D11+Simulador!$C$5+D11*Simulador!$C$7) -> 4146.7205 | E12: =D12*Simulador!$C$7 -> 33.173764 | F12: =F11+E12 -> 147.89428
B13: 9 | C13: =Simulador!$C$8+Simulador!$C$5*B13 -> 4500 | D13: =IF(Simulador!$C$9="SIM",(D12+Simulador!$C$5)*(1+Simulador!$C$7),D12+Simulador!$C$5+D12*Simulador!$C$7) -> 4683.8943 | E13: =D13*Simulador!$C$7 -> 37.471154 | F13: =F12+E13 -> 185.36543
B14: 10 | C14: =Simulador!$C$8+Simulador!$C$5*B14 -> 5000 | D14: =IF(Simulador!$C$9="SIM",(D13+Simulador!$C$5)*(1+Simulador!$C$7),D13+Simulador!$C$5+D13*Simulador!$C$7) -> 5225.3654 | E14: =D14*Simulador!$C$7 -> 41.802923 | F14: =F13+E14 -> 227.16836
B15: 11 | C15: =Simulador!$C$8+Simulador!$C$5*B15 -> 5500 | D15: =IF(Simulador!$C$9="SIM",(D14+Simulador!$C$5)*(1+Simulador!$C$7),D14+Simulador!$C$5+D14*Simulador!$C$7) -> 5771.1684 | E15: =D15*Simulador!$C$7 -> 46.169347 | F15: =F14+E15 -> 273.3377
B16: 12 | C16: =Simulador!$C$8+Simulador!$C$5*B16 -> 6000 | D16: =IF(Simulador!$C$9="SIM",(D15+Simulador!$C$5)*(1+Simulador!$C$7),D15+Simulador!$C$5+D15*Simulador!$C$7) -> 6321.3377 | E16: =D16*Simulador!$C$7 -> 50.570702 | F16: =F15+E16 -> 323.90841
B17: 13 | C17: =Simulador!$C$8+Simulador!$C$5*B17 -> 6500 | D17: =IF(Simulador!$C$9="SIM",(D16+Simulador!$C$5)*(1+Simulador!$C$7),D16+Simulador!$C$5+D16*Simulador!$C$7) -> 6875.9084 | E17: =D17*Simulador!$C$7 -> 55.007267 | F17: =F16+E17 -> 378.91567
B18: 14 | C18: =Simulador!$C$8+Simulador!$C$5*B18 -> 7000 | D18: =IF(Simulador!$C$9="SIM",(D17+Simulador!$C$5)*(1+Simulador!$C$7),D17+Simulador!$C$5+D17*Simulador!$C$7) -> 7434.9157 | E18: =D18*Simulador!$C$7 -> 59.479325 | F18: =F17+E18 -> 438.395
B19: 15 | C19: =Simulador!$C$8+Simulador!$C$5*B19 -> 7500 | D19: =IF(Simulador!$C$9="SIM",(D18+Simulador!$C$5)*(1+Simulador!$C$7),D18+Simulador!$C$5+D18*Simulador!$C$7) -> 7998.395 | E19: =D19*Simulador!$C$7 -> 63.98716 | F19: =F18+E19 -> 502.38216
B20: 16 | C20: =Simulador!$C$8+Simulador!$C$5*B20 -> 8000 | D20: =IF(Simulador!$C$9="SIM",(D19+Simulador!$C$5)*(1+Simulador!$C$7),D19+Simulador!$C$5+D19*Simulador!$C$7) -> 8566.3822 | E20: =D20*Simulador!$C$7 -> 68.531057 | F20: =F19+E20 -> 570.91322
B21: 17 | C21: =Simulador!$C$8+Simulador!$C$5*B21 -> 8500 | D21: =IF(Simulador!$C$9="SIM",(D20+Simulador!$C$5)*(1+Simulador!$C$7),D20+Simulador!$C$5+D20*Simulador!$C$7) -> 9138.9132 | E21: =D21*Simulador!$C$7 -> 73.111306 | F21: =F20+E21 -> 644.02452
B22: 18 | C22: =Simulador!$C$8+Simulador!$C$5*B22 -> 9000 | D22: =IF(Simulador!$C$9="SIM",(D21+Simulador!$C$5)*(1+Simulador!$C$7),D21+Simulador!$C$5+D21*Simulador!$C$7) -> 9716.0245 | E22: =D22*Simulador!$C$7 -> 77.728196 | F22: =F21+E22 -> 721.75272
... B244: 240 | C244: =Simulador!$C$8+Simulador!$C$5*B244 -> 120000 | D244: =IF(Simulador!$C$9="SIM",(D243+Simulador!$C$5)*(1+Simulador!$C$7),D243+Simulador!$C$5+D243*Simulador!$C$7) -> 363450.13 | E244: =D244*Simulador!$C$7 -> 2907.6011 | F244: =F243+E244 -> 245397.74

Sheet Gráficos
A1: Painel
A2: Sem gráficos neste arquivo.
